LICENSE
MANIFEST.in
README.md
requirements.txt
setup.cfg
setup.py
geolat/__init__.py
geolat/common.py
geolat/geolat.py
geolat.egg-info/PKG-INFO
geolat.egg-info/SOURCES.txt
geolat.egg-info/dependency_links.txt
geolat.egg-info/not-zip-safe
geolat.egg-info/top_level.txt
tests/test_geolat.py